Workbook

Sheet Dashboard
A1: Cash Flow Forecast
A3: Starting balance | B3: 1100
A4: Monthly income | B4: 4010
A5: Monthly expenses | B5: 3635
A6: One-time (month 2) | B6: 2200
A7: Horizon (months) | B7: 12
A9: Blue cells are inputs. Monthly sheet projects the running balance.

Sheet Monthly
A1: Month | B1: Date | C1: Income | D1: Expenses | E1: One-time | F1: Net | G1: Ending | H1: Status
A2: 1 | B2: 46266 | C2: =Dashboard!$B$4 | D2: =Dashboard!$B$5 | E2: =IF(A2=2,Dashboard!$B$6,0) | F2: =C2-D2-E2 | G2: =Dashboard!$B$3+F2 | H2: =IF(G2<0,"Negative","OK")
A3: 2 | B3: 46296 | C3: =Dashboard!$B$4 | D3: =Dashboard!$B$5 | E3: =IF(A3=2,Dashboard!$B$6,0) | F3: =C3-D3-E3 | G3: =G2+F3 | H3: =IF(G3<0,"Negative","OK")
A4: 3 | B4: 46327 | C4: =Dashboard!$B$4 | D4: =Dashboard!$B$5 | E4: =IF(A4=2,Dashboard!$B$6,0) | F4: =C4-D4-E4 | G4: =G3+F4 | H4: =IF(G4<0,"Negative","OK")
A5: 4 | B5: 46357 | C5: =Dashboard!$B$4 | D5: =Dashboard!$B$5 | E5: =IF(A5=2,Dashboard!$B$6,0) | F5: =C5-D5-E5 | G5: =G4+F5 | H5: =IF(G5<0,"Negative","OK")
A6: 5 | B6: 46388 | C6: =Dashboard!$B$4 | D6: =Dashboard!$B$5 | E6: =IF(A6=2,Dashboard!$B$6,0) | F6: =C6-D6-E6 | G6: =G5+F6 | H6: =IF(G6<0,"Negative","OK")
A7: 6 | B7: 46419 | C7: =Dashboard!$B$4 | D7: =Dashboard!$B$5 | E7: =IF(A7=2,Dashboard!$B$6,0) | F7: =C7-D7-E7 | G7: =G6+F7 | H7: =IF(G7<0,"Negative","OK")
A8: 7 | B8: 46447 | C8: =Dashboard!$B$4 | D8: =Dashboard!$B$5 | E8: =IF(A8=2,Dashboard!$B$6,0) | F8: =C8-D8-E8 | G8: =G7+F8 | H8: =IF(G8<0,"Negative","OK")
A9: 8 | B9: 46478 | C9: =Dashboard!$B$4 | D9: =Dashboard!$B$5 | E9: =IF(A9=2,Dashboard!$B$6,0) | F9: =C9-D9-E9 | G9: =G8+F9 | H9: =IF(G9<0,"Negative","OK")
A10: 9 | B10: 46508 | C10: =Dashboard!$B$4 | D10: =Dashboard!$B$5 | E10: =IF(A10=2,Dashboard!$B$6,0) | F10: =C10-D10-E10 | G10: =G9+F10 | H10: =IF(G10<0,"Negative","OK")
A11: 10 | B11: 46539 | C11: =Dashboard!$B$4 | D11: =Dashboard!$B$5 | E11: =IF(A11=2,Dashboard!$B$6,0) | F11: =C11-D11-E11 | G11: =G10+F11 | H11: =IF(G11<0,"Negative","OK")
A12: 11 | B12: 46569 | C12: =Dashboard!$B$4 | D12: =Dashboard!$B$5 | E12: =IF(A12=2,Dashboard!$B$6,0) | F12: =C12-D12-E12 | G12: =G11+F12 | H12: =IF(G12<0,"Negative","OK")
A13: 12 | B13: 46600 | C13: =Dashboard!$B$4 | D13: =Dashboard!$B$5 | E13: =IF(A13=2,Dashboard!$B$6,0) | F13: =C13-D13-E13 | G13: =G12+F13 | H13: =IF(G13<0,"Negative","OK")

Sheet Instructions
A1: Instructions
A3: 1. On Dashboard, type your starting balance, typical monthly income, and typical monthly expenses (blue cells).
A4: 2. Put a one-time hit (car repair, bonus as a negative one-time, etc.) in month 2 — or change the Monthly sheet formula in column E.
A5: 3. Ending balance on Monthly is the running cash. Status flags negative months in words.
A6: 4. This is the paid Harbor template companion to the free Cash Flow Forecast calculator.
A7: 5. Works in Excel and Google Sheets. Upload the .xlsx to Drive and Open with Google Sheets.
